Workbook

Sheet Dashboard
A1: Total | B1: Average Expense | C1: Most Expensive Category | D1: Least Expensive Category | J1: Total Number of Officers | K1: Average Expense per Officer | L1: Highest Allocation | M1: Lowest Allocation
A2: =Expenses_per_Category[[#TOTALS],[Total Expense]] -> 176820 | B2: =AVERAGE('Raw Data'!E2:E1000) -> 2947 | C2: =MAX(Expenses_per_Category[Total Expense]) -> 61500 | D2: =MIN(Expenses_per_Category[Total Expense]) -> 7170 | J2: =COUNTA(Category!E2:E1000) -> 6 | K2: =AVERAGE('Analytics Summary'!B2:B7) -> 29470 | L2: =MAX('Analytics Summary'!B2:B7) -> 83750 | M2: =MIN('Analytics Summary'!B2:B7) -> 4520

Sheet Analytics Summary
A1: Responsible Officer | B1: Actual Cost Per Officer | C1: Estimated Cost Per Officer | G1: Date | H1: Number of Transactions
A2: A. Santos | B2: =SUMIF(University_Event_Expenses[Responsible Officer],A2,University_Event_Expenses[Actual Cost]) -> 30350 | C2: =SUMIF(University_Event_Expenses[Responsible Officer],A2,University_Event_Expenses[Estimated Cost]) -> 29900 | G2: {=UNIQUE('Raw Data'!G2:G1000)} -> 46113 | H2: =COUNTIF('Raw Data'!G2:G1000,G2) -> 6
A3: J. Cruz | B3: =SUMIF(University_Event_Expenses[Responsible Officer],A3,University_Event_Expenses[Actual Cost]) -> 44650 | C3: =SUMIF(University_Event_Expenses[Responsible Officer],A3,University_Event_Expenses[Estimated Cost]) -> 43400 | G3: 46117 | H3: =COUNTIF('Raw Data'!G3:G1000,G3) -> 13
A4: M. Dela Rosa | B4: =SUMIF(University_Event_Expenses[Responsible Officer],A4,University_Event_Expenses[Actual Cost]) -> 8200 | C4: =SUMIF(University_Event_Expenses[Responsible Officer],A4,University_Event_Expenses[Estimated Cost]) -> 8100 | G4: 46109 | H4: =COUNTIF('Raw Data'!G4:G1000,G4) -> 4
A5: H. Valenzuela | B5: =SUMIF(University_Event_Expenses[Responsible Officer],A5,University_Event_Expenses[Actual Cost]) -> 4520 | C5: =SUMIF(University_Event_Expenses[Responsible Officer],A5,University_Event_Expenses[Estimated Cost]) -> 4500 | G5: 46116 | H5: =COUNTIF('Raw Data'!G5:G1000,G5) -> 10
A6: N. Corpuz | B6: =SUMIF(University_Event_Expenses[Responsible Officer],A6,University_Event_Expenses[Actual Cost]) -> 83750 | C6: =SUMIF(University_Event_Expenses[Responsible Officer],A6,University_Event_Expenses[Estimated Cost]) -> 81500 | G6: 46114 | H6: =COUNTIF('Raw Data'!G6:G1000,G6) -> 6
A7: W. Gomez | B7: =SUMIF(University_Event_Expenses[Responsible Officer],A7,University_Event_Expenses[Actual Cost]) -> 5350 | C7: =SUMIF(University_Event_Expenses[Responsible Officer],A7,University_Event_Expenses[Estimated Cost]) -> 5400 | G7: 46111 | H7: =COUNTIF('Raw Data'!G7:G1000,G7) -> 3
A8: Total | B8: =SUM(B2:B7) -> 176820 | C8: =SUM(C2:C7) -> 172800 | G8: 46110 | H8: =COUNTIF('Raw Data'!G8:G1000,G8) -> 4
G9: 46118 | H9: =COUNTIF('Raw Data'!G9:G1000,G9) -> 5
G10: 46115 | H10: =COUNTIF('Raw Data'!G10:G1000,G10) -> 7
A11: Summary | B11: Total | G11: 46112 | H11: =COUNTIF('Raw Data'!G11:G1000,G11) -> 2
A12: Paid | B12: =COUNTIF(University_Event_Expenses[Payment Status],A12) -> 39
A13: Pending | B13: =COUNTIF(University_Event_Expenses[Payment Status],A13) -> 15
A14: Cancelled | B14: =COUNTIF(University_Event_Expenses[Payment Status],A14) -> 6
A15: Total | B15: =SUM(B12:B14) -> 60
A18: Expense Category | B18: Total Category | C18: Highest Expense | D18: Lowest Expense | E18: Total Expense
A19: Catering | B19: =COUNTIF(University_Event_Expenses[Expense Category],A19) -> 9 | C19: =MAXIFS(University_Event_Expenses[Actual Cost], University_Event_Expenses[Expense Category], A19) -> 3400 | D19: =MINIFS(University_Event_Expenses[Actual Cost], University_Event_Expenses[Expense Category], A19) -> 2750 | E19: =SUMIF(University_Event_Expenses[Expense Category],A19,University_Event_Expenses[Actual Cost]) -> 27700
A20: Venue | B20: =COUNTIF(University_Event_Expenses[Expense Category],A20) -> 5 | C20: =MAXIFS(University_Event_Expenses[Actual Cost], University_Event_Expenses[Expense Category], A20) -> 13000 | D20: =MINIFS(University_Event_Expenses[Actual Cost], University_Event_Expenses[Expense Category], A20) -> 12000 | E20: =SUMIF(University_Event_Expenses[Expense Category],A20,University_Event_Expenses[Actual Cost]) -> 61500
A21: Sound & Lights | B21: =COUNTIF(University_Event_Expenses[Expense Category],A21) -> 8 | C21: =MAXIFS(University_Event_Expenses[Actual Cost], University_Event_Expenses[Expense Category], A21) -> 4900 | D21: =MINIFS(University_Event_Expenses[Actual Cost], University_Event_Expenses[Expense Category], A21) -> 2900 | E21: =SUMIF(University_Event_Expenses[Expense Category],A21,University_Event_Expenses[Actual Cost]) -> 32700
A22: Marketing | B22: =COUNTIF(University_Event_Expenses[Expense Category],A22) -> 10 | C22: =MAXIFS(University_Event_Expenses[Actual Cost], University_Event_Expenses[Expense Category], A22) -> 1900 | D22: =MINIFS(University_Event_Expenses[Actual Cost], University_Event_Expenses[Expense Category], A22) -> 880 | E22: =SUMIF(University_Event_Expenses[Expense Category],A22,University_Event_Expenses[Actual Cost]) -> 13550
A23: Logistics | B23: =COUNTIF(University_Event_Expenses[Expense Category],A23) -> 8 | C23: =MAXIFS(University_Event_Expenses[Actual Cost], University_Event_Expenses[Expense Category], A23) -> 1900 | D23: =MINIFS(University_Event_Expenses[Actual Cost], University_Event_Expenses[Expense Category], A23) -> 950 | E23: =SUMIF(University_Event_Expenses[Expense Category],A23,University_Event_Expenses[Actual Cost]) -> 11950
A24: Security | B24: =COUNTIF(University_Event_Expenses[Expense Category],A24) -> 11 | C24: =MAXIFS(University_Event_Expenses[Actual Cost], University_Event_Expenses[Expense Category], A24) -> 2400 | D24: =MINIFS(University_Event_Expenses[Actual Cost], University_Event_Expenses[Expense Category], A24) -> 1500 | E24: =SUMIF(University_Event_Expenses[Expense Category],A24,University_Event_Expenses[Actual Cost]) -> 22250
A25: Miscellaneous | B25: =COUNTIF(University_Event_Expenses[Expense Category],A25) -> 9 | C25: =MAXIFS(University_Event_Expenses[Actual Cost], University_Event_Expenses[Expense Category], A25) -> 920 | D25: =MINIFS(University_Event_Expenses[Actual Cost], University_Event_Expenses[Expense Category], A25) -> 650 | E25: =SUMIF(University_Event_Expenses[Expense Category],A25,University_Event_Expenses[Actual Cost]) -> 7170
A26: Total | B26: =SUM(B19:B25) -> 60 | C26: N/A | D26: N/A | E26: =SUM(E19:E25) -> 176820

Sheet Raw Data
A1: UID | B1: Expense Category | C1: Vendor | D1: Estimated Cost | E1: Actual Cost | F1: Payment Status | G1: Transaction Date | H1: Event Date | I1: Responsible Officer
A2: 1 | B2: Catering | C2: Jollibee | D2: 3200 | E2: 3000 | F2: Paid | G2: 46113 | H2: 46118 | I2: A. Santos
A3: 2 | B3: Catering | C3: Jollibee | D3: 3200 | E3: 3100 | F3: Paid | G3: 46113 | H3: 46119 | I3: A. Santos
A4: 3 | B4: Catering | C4: Jollibee | D4: 3200 | E4: 3300 | F4: Paid | G4: 46113 | H4: 46120 | I4: A. Santos
A5: 4 | B5: Catering | C5: Jollibee | D5: 3200 | E5: 3150 | F5: Pending | G5: 46117 | H5: 46121 | I5: A. Santos
A6: 5 | B6: Catering | C6: Jollibee | D6: 3200 | E6: 3400 | F6: Pending | G6: 46117 | H6: 46122 | I6: A. Santos
A7: 6 | B7: Venue | C7: SMX Convention Center | D7: 12000 | E7: 12000 | F7: Paid | G7: 46109 | H7: 46118 | I7: N. Corpuz
A8: 7 | B8: Venue | C8: SMX Convention Center | D8: 12000 | E8: 12000 | F8: Paid | G8: 46109 | H8: 46119 | I8: N. Corpuz
A9: 8 | B9: Venue | C9: SMX Convention Center | D9: 12000 | E9: 12500 | F9: Paid | G9: 46109 | H9: 46120 | I9: N. Corpuz
A10: 9 | B10: Venue | C10: SMX Convention Center | D10: 12000 | E10: 12000 | F10: Paid | G10: 46109 | H10: 46121 | I10: N. Corpuz
A11: 10 | B11: Venue | C11: SMX Convention Center | D11: 12000 | E11: 13000 | F11: Pending | G11: 46116 | H11: 46122 | I11: N. Corpuz
A12: 11 | B12: Sound & Lights | C12: ABC Sound Systems | D12: 4500 | E12: 4700 | F12: Paid | G12: 46114 | H12: 46118 | I12: J. Cruz
A13: 12 | B13: Sound & Lights | C13: ABC Sound Systems | D13: 4500 | E13: 4600 | F13: Paid | G13: 46114 | H13: 46119 | I13: J. Cruz
... A61: 60 | B61: Marketing | C61: Email Campaign Tool | D61: 900 | E61: 950 | F61: Pending | G61: 46118 | H61: 46122 | I61: M. Dela Rosa

Sheet Timeline of Transactions

Sheet Category
A1: Expense Category | B1: Vendor | C1: Payment Status | D1: Event Date | E1: Officer
A2: Catering | B2: Jollibee | C2: Paid | D2: 46118 | E2: A. Santos
A3: Venue | B3: SMX Convention Center | C3: Pending | D3: 46119 | E3: J. Cruz
A4: Sound & Lights | B4: ABC Sound Systems | C4: Cancelled | D4: 46120 | E4: M. Dela Rosa
A5: Marketing | B5: Facebook Ads | D5: 46121 | E5: H. Valenzuela
A6: Logistics | B6: Print Hub | D6: 46122 | E6: N. Corpuz
A7: Security | B7: Grab Transport | E7: W. Gomez
A8: Miscellaneous | B8: LBC Express
B9: SecureForce
B10: Campus Guards
B11: Office Depot
B12: Water Refilling Station
B13: Greenwich
B14: Campus Tarpaulin Shop
B15: University Motor Pool
B16: Campus AV Services
B17: First Aid Supplies Co.
B18: Barangay Security Unit
B19: Email Campaign Tool

Sheet Reflections
A1: Questions | B1: Kim, Andrew Min Yeop P. | C1: Escarrilla, Luis Angelo T. | D1: Tangcay | E1: Salise | F1: Dumagan | G1: Enriquez | H1: Ingente
A2: Their assigned role | B2: I am the Project Manager for this lab activity. To fulfill my role, I provided the team with the workflow, coordinated with the team to accomplish the deliverables, created a timeline based on the transaction and event dates, and assisted with the creation of the visualizations found in the dashboard. The biggest challenge was starting the project, inferrable from the delayed submission. Additionally, finding the right balance between pressure (so that things get done) and leniency (so that morale does not drop) was also quite a challenge. Through this project, aside from learning how to manage a team, I learned how to customize charts for better aesthetic quality and analytical clarity in Sheets. | C2: I am the Data Entry and Cleaning Specialist. I was responsible for designing and preparing the shared dataset used by the group. I structured the raw data with clean, standardized masterlists and ensured all data followed consistent formatting for dates and currency. I also normalized multi-day expenses into daily entries to support accurate analysis and pivot table creation. One challenge I faced was balancing realism with analytical clarity, especially when deciding how to represent expenses that spanned multiple event days. Through this process, I learned the importance of data normalization and how early design decisions directly affect formulas, pivot tables, and dashboards. | D2: I am the Formula & Logic Specialist. I did our document formula and logic setup to make our event expense tracking much faster and more automated. My biggest challenge was definitely troubleshooting "ghost spaces" in the cells that were making my COUNTIF formulas return the wrong numbers. Through this, I learned how to use custom number formatting to get that professional ₱ symbol to show up correctly without breaking the math. It was a great way to see how setting up the right formulas can save our whole group a lot of manual work. | E2: I am the Pivot Specialist for this project. I made the Costs Incurred Table for the Analytics Summary spreadsheet. Some challenges I have faced were how the data is being displayed, or rather, filtered. To solve this problem, I used the SUMIF function and added a filter that sorts the total costs incurred by the respective officer. Both the actual and estimated costs are filtered through. With that said, I did learn an essential skill while performing this activity. It taught me how to create pivot tables and simplify large datasets in order to quickly summarize data that can be easily digested. This skill is really important to learn especially in the 21st century. | F2: I am the Dashboard designer for this lab activity, I was responsible for building the visual dashboard like charts in order to present data in a more clear way. I focused on organizing information that made the dashboard easy to understand. One challenge I encountered was determining the best way to visualize the data so that it can accurately represent needed information. With this project I improved my skills in creating easy to understand charts that can effectively communicate key insights. | G2: I am the Quality Assurance & Documentation Officer for this lab activity, responsible for systematically checking for errors, adding constructive comments for improvement, and compiling the final summary reflection. I focused on ensuring that all project documentation was accurate, consistent to the rubrics before finalization. One challenge I encountered was maintaining strict version control when multiple team members were submitting updates simultaneously. With this project, I improved my skills in creating and auditing technical documentation, ensuring I can effectively identify risks and assure quality in future projects.
A3: What they contributed
A4: Challenges faced
A5: One new skill learned
